{"0":"_Points","1":"_Round","2":"_Zombies","3":"$ {}","4":"Round: {}","5":"Zombies in map: {}","6":"_Primary_Slot","7":"Replace Primary","8":"_Primary_Slot_Button","9":"_Secondary_Slot","10":"Replace Secondary","11":"_Secondary_Slot_Button","12":"_Cancel","13":"Cancel","14":"_Cancel_Button","15":"_Weapon_Name","16":"_Weapon_Price","17":"Price: ${}","18":"{} ${}","19":"Required Points: ${}","20":"_Next_Round","21":"Round complete! Get ready for more.","22":"ADDED TO MUCH AMMOS","23":"AK4D","24":"B36A4","25":"KORD 6P67","26":"L85A3","27":"M433","28":"NVO-228E","29":"SOR-556 MK2","30":"TR-7","31":"AK-205","32":"GRT-BC","33":"M277","34":"M417 A2","35":"M4A1","36":"QBZ-192","37":"SG 553R","38":"LMR27","39":"M39 EMR","40":"SVDM","41":"SVK-8.6","42":"DRS-IAR","43":"KTS100 MK8","44":"L110","45":"M/60","46":"M123K","47":"M240L","48":"M250","49":"RPKM","50":"18.5KS-K","51":"M1014","52":"M87A1","53":"ES 5.7","54":"M44","55":"M45A1","56":"P18","57":"KV9","58":"PW5A3","59":"#####","60":"SCW-10","61":"SGX","62":"SL9","63":"UMG-40","64":"USG-90","65":"M2010 ESR","66":"PSR","67":"SV-98"}